odoo/addons/kpi_dashboard_test/README.rst
odoo/addons/kpi_dashboard_test/__init__.py
odoo/addons/kpi_dashboard_test/__manifest__.py
odoo/addons/kpi_dashboard_test/demo/demo_dashboard.xml
odoo/addons/kpi_dashboard_test/i18n/kpi_dashboard_test.pot
odoo/addons/kpi_dashboard_test/models/__init__.py
odoo/addons/kpi_dashboard_test/models/kpi_kpi.py
odoo/addons/kpi_dashboard_test/readme/CONTRIBUTORS.rst
odoo/addons/kpi_dashboard_test/readme/DESCRIPTION.rst
odoo/addons/kpi_dashboard_test/static/description/icon.png
odoo/addons/kpi_dashboard_test/static/description/index.html
odoo/addons/kpi_dashboard_test/tests/__init__.py
odoo/addons/kpi_dashboard_test/tests/test_kpi_dashboard.py
odoo12_addon_kpi_dashboard_test-12.0.1.0.1.dist-info/METADATA
odoo12_addon_kpi_dashboard_test-12.0.1.0.1.dist-info/WHEEL
odoo12_addon_kpi_dashboard_test-12.0.1.0.1.dist-info/top_level.txt
odoo12_addon_kpi_dashboard_test-12.0.1.0.1.dist-info/RECORD
